PySimpleGUI_Events/__init__.py
PySimpleGUI_Events/application_state.py
PySimpleGUI_Events/event_manager.py
PySimpleGUI_Events/handler.py
PySimpleGUI_Events-0.0.3.dist-info/LICENSE
PySimpleGUI_Events-0.0.3.dist-info/METADATA
PySimpleGUI_Events-0.0.3.dist-info/WHEEL
PySimpleGUI_Events-0.0.3.dist-info/top_level.txt
PySimpleGUI_Events-0.0.3.dist-info/RECORD
