Metadata-Version: 2.1
Name: PySimpleGUI_Events
Version: 0.0.3
Summary: A simple event handler system for PySimpleGUI
Home-page: https://github.com/jyurkiw/PySimpleGUI_Events
Author: Jeffrey Yurkiw
Author-email: jyurkiw@yahoo.com
License: MIT
Keywords: gui events
Platform: UNKNOWN
Classifier: Development Status :: 3 - Alpha
Classifier: Topic :: Utilities
Classifier: License :: OSI Approved :: MIT License
License-File: LICENSE
